ice_client/README.md
ice_client/__init__.py
ice_client/client.py
ice_client/models.py
iceos_client-0.1.2.dist-info/METADATA
iceos_client-0.1.2.dist-info/WHEEL
iceos_client-0.1.2.dist-info/RECORD
