Metadata-Version: 2.3
Name: iceos-client
Version: 0.1.2
Summary: Typed async Python client for the iceOS Orchestrator API
License: MIT
Keywords: iceos,client,async,httpx,orchestrator,mcp,agents
Author: iceOS Developers
Author-email: dev@iceos.dev
Requires-Python: >=3.11,<4.0
Classifier: Development Status :: 3 - Alpha
Classifier: Intended Audience :: Developers
Classifier: License :: OSI Approved :: MIT License
Classifier: Programming Language :: Python
Classifier: Programming Language :: Python :: 3
Classifier: Programming Language :: Python :: 3.11
Classifier: Programming Language :: Python :: 3.12
Classifier: Programming Language :: Python :: 3.13
Classifier: Topic :: Software Development :: Libraries
Classifier: Topic :: Software Development :: Libraries :: Python Modules
Requires-Dist: PyYAML (>=6.0.2,<7.0.0)
Requires-Dist: httpx (>=0.27.2,<0.28.0)
Requires-Dist: pydantic (>=2.8.2,<3.0.0)
Project-URL: Homepage, https://github.com/noozrad/iceOS
Project-URL: Repository, https://github.com/noozrad/iceOS
